ncert_learn/__init__.py
ncert_learn/advancedmodeforpg.py
ncert_learn/api.py
ncert_learn/area.py
ncert_learn/binary.py
ncert_learn/cmd.py
ncert_learn/codeformatter.py
ncert_learn/conversions.py
ncert_learn/cryptography_.py
ncert_learn/csv_.py
ncert_learn/dat.py
ncert_learn/dictfncs.py
ncert_learn/encoding.py
ncert_learn/engine.py
ncert_learn/fileaccess.py
ncert_learn/get.py
ncert_learn/getfunctions.py
ncert_learn/googlesearch_.py
ncert_learn/intfncs.py
ncert_learn/lstfncs.py
ncert_learn/main.py
ncert_learn/mathematical.py
ncert_learn/miner.py
ncert_learn/ml.py
ncert_learn/mysql_.py
ncert_learn/newer.py
ncert_learn/nmap.py
ncert_learn/nmapinstall.py
ncert_learn/numerical.py
ncert_learn/os.py
ncert_learn/packageinstall.py
ncert_learn/pdfextract.py
ncert_learn/plotting.py
ncert_learn/search_.py
ncert_learn/sort.py
ncert_learn/sqlmap.py
ncert_learn/stkdict.py
ncert_learn/stklist.py
ncert_learn/strfncs.py
ncert_learn/support.py
ncert_learn/text.py
ncert_learn/time.py
ncert_learn/tree.py
ncert_learn/xampp.py
ncert_learn/zip.py
ncert_learn/engine/libgcc_s_seh-1.dll
ncert_learn/engine/libstdc++-6.dll
ncert_learn/engine/loss_functions.dll
ncert_learn/engine/neural_network_layers.dll
ncert_learn/engine/optimizers.dll
ncert_learn/engine/tensor_operations.dll
ncert_learn/sqlmap/.gitattributes
ncert_learn/sqlmap/.gitignore
ncert_learn/sqlmap/.pylintrc
ncert_learn/sqlmap/LICENSE
ncert_learn/sqlmap/README.md
ncert_learn/sqlmap/sqlmap.conf
ncert_learn/sqlmap/sqlmap.py
ncert_learn/sqlmap/sqlmapapi.py
ncert_learn/sqlmap/sqlmapapi.yaml
ncert_learn/sqlmap/.github/CODE_OF_CONDUCT.md
ncert_learn/sqlmap/.github/CONTRIBUTING.md
ncert_learn/sqlmap/.github/FUNDING.yml
ncert_learn/sqlmap/.github/ISSUE_TEMPLATE/bug_report.md
ncert_learn/sqlmap/.github/ISSUE_TEMPLATE/feature_request.md
ncert_learn/sqlmap/.github/workflows/tests.yml
ncert_learn/sqlmap/data/html/index.html
ncert_learn/sqlmap/data/procs/README.txt
ncert_learn/sqlmap/data/procs/mssqlserver/activate_sp_oacreate.sql
ncert_learn-5.5.7.dist-info/LICENSE
ncert_learn-5.5.7.dist-info/METADATA
ncert_learn-5.5.7.dist-info/WHEEL
ncert_learn-5.5.7.dist-info/top_level.txt
ncert_learn-5.5.7.dist-info/RECORD
