Metadata-Version: 2.1
Name: ncert_learn
Version: 5.5.7
Summary: A Python Module for NCERT Class 12 Computer Science - Learn Python and MySQL with ease!
Home-page: https://github.com/hejhdiss/ncert_learn
Author: Muhammed Shafin P
Author-email: hejhdiss@example.com
Project-URL: Bug Tracker, https://github.com/hejhdiss/ncert_learn/issues
Project-URL: Documentation, https://hejhdiss.github.io/ncert_learn-website/
Project-URL: Instagram, https://www.instagram.com/ncert_learn
Classifier: Programming Language :: Python :: 3
Classifier: License :: OSI Approved :: MIT License
Classifier: Operating System :: OS Independent
Requires-Python: >=3.6
License-File: LICENSE
Requires-Dist: mysql-connector-python
Requires-Dist: pytest
Requires-Dist: tox
Requires-Dist: requests
Requires-Dist: psutil
Requires-Dist: beautifulsoup4
Requires-Dist: googlesearch-python
Requires-Dist: python-nmap
Requires-Dist: PyPDF2
Requires-Dist: numpy
Requires-Dist: matplotlib
Requires-Dist: brotli
Requires-Dist: autopep8
Requires-Dist: pylint
Requires-Dist: pandas
Requires-Dist: scikit-learn
Requires-Dist: joblib
Requires-Dist: cryptography
Requires-Dist: phonenumbers
Requires-Dist: bcrypt
